club255/__init__.py
club255/client.py
club255/const.py
club255/exception.py
club255/model.py
club255-0.1.2.dist-info/LICENSE
club255-0.1.2.dist-info/METADATA
club255-0.1.2.dist-info/WHEEL
club255-0.1.2.dist-info/RECORD
