Metadata-Version: 2.1
Name: club255
Version: 0.1.2
Summary: 
License: MIT
Author: eya46
Author-email: 61458340+eya46@users.noreply.github.com
Requires-Python: >=3.9,<4.0
Classifier: License :: OSI Approved :: MIT License
Classifier: Programming Language :: Python :: 3
Classifier: Programming Language :: Python :: 3.9
Classifier: Programming Language :: Python :: 3.10
Classifier: Programming Language :: Python :: 3.11
Classifier: Programming Language :: Python :: 3.12
Requires-Dist: httpx (>=0.27.2,<0.28.0)
Requires-Dist: pydantic (>=2.9.1,<3.0.0)
Requires-Dist: yarl (>=1.11.1,<2.0.0)
